pupil_labs/camera/__init__.py
pupil_labs/camera/custom_types.py
pupil_labs/camera/py.typed
pupil_labs/camera/radial.py
pupil_labs/camera/utils.py
pupil_labs/camera/assets/__init__.py
pupil_labs/camera/assets/chessboard.jpeg
pupil_labs_camera-1.1.0.dist-info/METADATA
pupil_labs_camera-1.1.0.dist-info/WHEEL
pupil_labs_camera-1.1.0.dist-info/licenses/LICENSE
pupil_labs_camera-1.1.0.dist-info/RECORD
