Metadata-Version: 2.4
Name: pupil-labs-camera
Version: 1.1.0
Summary: Utilities for handling cameras.
Project-URL: Homepage, https://pupil-labs.github.io/pl-camera
Project-URL: Documentation, https://pupil-labs.github.io/pl-camera
Project-URL: Repository, https://github.com/pupil-labs/pl-camera
Project-URL: Issues, https://github.com/pupil-labs/pl-camera/issues
Author-email: Pupil Labs GmbH <info@pupil-labs.com>
License: MIT
License-File: LICENSE
Classifier: Intended Audience :: Developers
Classifier: Programming Language :: Python
Classifier: Programming Language :: Python :: 3
Classifier: Programming Language :: Python :: 3.10
Classifier: Programming Language :: Python :: 3.11
Classifier: Programming Language :: Python :: 3.12
Classifier: Programming Language :: Python :: 3.13
Classifier: Topic :: Software Development :: Libraries :: Python Modules
Requires-Python: <4.0,>=3.10
Requires-Dist: numpy
Requires-Dist: opencv-python>=4.11.0.86
